ElvantoAPI/__init__.py
ElvantoAPI-1.4.2.dist-info/DESCRIPTION.rst
ElvantoAPI-1.4.2.dist-info/METADATA
ElvantoAPI-1.4.2.dist-info/RECORD
ElvantoAPI-1.4.2.dist-info/WHEEL
ElvantoAPI-1.4.2.dist-info/metadata.json
ElvantoAPI-1.4.2.dist-info/top_level.txt
