Metadata-Version: 2.0
Name: ElvantoAPI
Version: 1.4.2
Summary: Python API Wrapper for Elvanto Systems
Home-page: https://github.com/elvanto/api-py
Author: Elvanto
Author-email: support@elvanto.com
License: UNKNOWN
Platform: UNKNOWN
Requires-Dist: requests
